functionfinder/__init__.py
functionfinder/main.py
functionfinder/runner.py
functionvis/__init__.py
functionvis/main.py
functionvis/runner.py
functionvis-0.1.6.dist-info/METADATA
functionvis-0.1.6.dist-info/WHEEL
functionvis-0.1.6.dist-info/top_level.txt
functionvis-0.1.6.dist-info/RECORD
