Metadata-Version: 2.1
Name: functionvis
Version: 0.1.6
Summary: Visualize all functions and classes in a directory
Home-page: https://github.com/SubhadityaMukherjee/functionFinder
Author: Subhaditya Mukherjee
Author-email: msubhaditya@gmail.com
License: MIT
Platform: UNKNOWN
Classifier: Programming Language :: Python :: 3
Classifier: License :: OSI Approved :: MIT License
Classifier: Operating System :: OS Independent
Requires-Python: >=3.6
